ceb_pdf_extractor/__init__.py
ceb_pdf_extractor/account_query.py
ceb_pdf_extractor/account_query_other.py
ceb_pdf_extractor/cli.py
ceb_pdf_extractor/company.py
ceb_pdf_extractor/nowatermark.py
ceb_pdf_extractor/personal.py
ceb_pdf_extractor-2.0.2.dist-info/licenses/LICENSE
ceb_pdf_extractor-2.0.2.dist-info/METADATA
ceb_pdf_extractor-2.0.2.dist-info/WHEEL
ceb_pdf_extractor-2.0.2.dist-info/entry_points.txt
ceb_pdf_extractor-2.0.2.dist-info/top_level.txt
ceb_pdf_extractor-2.0.2.dist-info/RECORD
