Metadata-Version: 2.4
Name: ceb-pdf-extractor
Version: 2.0.2
Summary: 光大银行PDF对账单提取工具 - 支持五种不同版式的对账单提取
Home-page: https://github.com/liangjingcheng/CEBBANK-statement-cleaning
Author: 梁京成
Author-email: 2046175864@qq.com
Maintainer: 梁京成
Maintainer-email: 2046175864@qq.com
License: MIT
Project-URL: Homepage, https://github.com/yourusername/ceb-pdf-extractor
Project-URL: Documentation, https://github.com/yourusername/ceb-pdf-extractor/wiki
Project-URL: Bug Reports, https://github.com/yourusername/ceb-pdf-extractor/issues
Project-URL: Source Code, https://github.com/yourusername/ceb-pdf-extractor
Project-URL: Changelog, https://github.com/yourusername/ceb-pdf-extractor/blob/main/CHANGELOG.md
Keywords: bank,pdf,extractor,ceb,excel,光大银行,对账单,PDF解析,表格提取,financial,document,parser
Platform: any
Classifier: Development Status :: 5 - Production/Stable
Classifier: Intended Audience :: Financial and Insurance Industry
Classifier: Intended Audience :: End Users/Desktop
Classifier: Intended Audience :: Developers
Classifier: Topic :: Office/Business :: Financial
Classifier: Topic :: Software Development :: Libraries :: Python Modules
Classifier: Topic :: Utilities
Classifier: License :: OSI Approved :: MIT License
Classifier: Programming Language :: Python :: 3
Classifier: Programming Language :: Python :: 3.7
Classifier: Programming Language :: Python :: 3.8
Classifier: Programming Language :: Python :: 3.9
Classifier: Programming Language :: Python :: 3.10
Classifier: Programming Language :: Python :: 3.11
Classifier: Programming Language :: Python :: 3.12
Classifier: Operating System :: OS Independent
Classifier: Operating System :: Microsoft :: Windows
Classifier: Operating System :: POSIX :: Linux
Classifier: Operating System :: MacOS :: MacOS X
Requires-Python: >=3.7
License-File: LICENSE
Requires-Dist: PyMuPDF>=1.23.0
Requires-Dist: openpyxl>=3.1.0
Provides-Extra: dev
Requires-Dist: pytest>=7.0.0; extra == "dev"
Requires-Dist: pytest-cov>=4.0.0; extra == "dev"
Requires-Dist: black>=22.0.0; extra == "dev"
Requires-Dist: flake8>=5.0.0; extra == "dev"
Requires-Dist: mypy>=0.990; extra == "dev"
Requires-Dist: twine>=4.0.0; extra == "dev"
Requires-Dist: wheel>=0.37.0; extra == "dev"
Requires-Dist: build>=0.9.0; extra == "dev"
Provides-Extra: test
Requires-Dist: pytest>=7.0.0; extra == "test"
Requires-Dist: pytest-cov>=4.0.0; extra == "test"
Dynamic: author
Dynamic: author-email
Dynamic: classifier
Dynamic: description
Dynamic: description-content-type
Dynamic: home-page
Dynamic: keywords
Dynamic: license
Dynamic: license-file
Dynamic: maintainer
Dynamic: maintainer-email
Dynamic: platform
Dynamic: project-url
Dynamic: provides-extra
Dynamic: requires-dist
Dynamic: requires-python
Dynamic: summary
